ttx/__init__.py
ttx/api_client.py
ttx/api_response.py
ttx/configuration.py
ttx/exceptions.py
ttx/py.typed
ttx/rest.py
ttx/api/__init__.py
ttx/api/creators_api.py
ttx/api/players_api.py
ttx/api/sessions_api.py
ttx/api/transactions_api.py
ttx/models/__init__.py
ttx/models/create_transaction_dto.py
ttx/models/creator_dto.py
ttx/models/creator_order_by.py
ttx/models/creator_partial_dto.py
ttx/models/creator_partial_dto_pagination_dto.py
ttx/models/creator_rarity_dto.py
ttx/models/creator_share_dto.py
ttx/models/creator_transaction_dto.py
ttx/models/discord_token_dto.py
ttx/models/link_discord_twitch_dto.py
ttx/models/loot_box_dto.py
ttx/models/loot_box_result_dto.py
ttx/models/model_id.py
ttx/models/order_direction.py
ttx/models/player_dto.py
ttx/models/player_dto_pagination_dto.py
ttx/models/player_order_by.py
ttx/models/player_partial_dto.py
ttx/models/player_share_dto.py
ttx/models/player_transaction_dto.py
ttx/models/player_type.py
ttx/models/portfolio_snapshot_dto.py
ttx/models/rarity.py
ttx/models/stream_status_dto.py
ttx/models/time_step.py
ttx/models/token_dto.py
ttx/models/transaction_action.py
ttx/models/twitch_user_dto.py
ttx/models/vote_dto.py
ttx-1.0.0.dist-info/licenses/LICENSE
ttx-1.0.0.dist-info/METADATA
ttx-1.0.0.dist-info/WHEEL
ttx-1.0.0.dist-info/top_level.txt
ttx-1.0.0.dist-info/RECORD
